rtl/sram_behav.v
module sram_behav #(
  parameter ADDR_W = 8,   // 256 words
  parameter DATA_W = 32
)(
  input  wire              clk,
  input  wire              cs,   // active high
  input  wire              we,   // 1=write, 0=read
  input  wire [ADDR_W-1:0] addr,
  input  wire [DATA_W-1:0] din,
  output wire [DATA_W-1:0] dout
);
  reg [DATA_W-1:0] mem [0:(1<<ADDR_W)-1];

  // Ghi đồng bộ
  always @(posedge clk) begin
    if (cs && we) mem[addr] <= din;
  end

  // Đọc bất đồng bộ, không gate cs để tránh thấy 0
  assign dout = mem[addr];

endmodule

rtl/mem_ctrl.v
module mem_ctrl #(
  parameter ADDR_W = 8,
  parameter DATA_W = 32
)(
  input  wire              clk,
  input  wire              rstn,
  // APB-lite style
  input  wire              psel,
  input  wire              penable,
  input  wire              pwrite,
  input  wire [ADDR_W-1:0] paddr,
  input  wire [DATA_W-1:0] pwdata,
  output reg  [DATA_W-1:0] prdata,
  output reg               pready,
  // SRAM side
  output reg               s_cs,
  output reg               s_we,
  output reg  [ADDR_W-1:0] s_addr,
  output reg  [DATA_W-1:0] s_din,
  input  wire [DATA_W-1:0] s_dout
);

  reg pending; // đánh dấu có request cần trả lời ở chu kỳ kế tiếp

  always @(posedge clk or negedge rstn) begin
    if (!rstn) begin
      pready  <= 1'b0;
      prdata  <= '0;
      s_cs    <= 1'b0;
      s_we    <= 1'b0;
      s_addr  <= '0;
      s_din   <= '0;
      pending <= 1'b0;
    end else begin
      pready  <= pending;   // trả lời sau 1 chu kỳ
      if (pending) begin
        prdata <= s_dout;   // s_dout đã ổn định sau khi s_addr set ở chu kỳ trước
      end
      pending <= 1'b0;
      s_cs    <= 1'b0;
      s_we    <= 1'b0;

      if (psel && penable) begin
        s_cs    <= 1'b1;
        s_we    <= pwrite;
        s_addr  <= paddr;
        s_din   <= pwdata;
        pending <= 1'b1;   // sẽ pready ở chu kỳ kế
      end
    end
  end
endmodule

tb/tb_top.v
`timescale 1ns/1ps
module tb_top;
  reg clk=0, rstn=0;
  always #5 clk = ~clk; // 100 MHz

  reg psel=0, penable=0, pwrite=0;
  reg [7:0] paddr=0;
  reg [31:0] pwdata=0;
  wire [31:0] prdata;
  wire pready;

  wire s_cs, s_we;
  wire [7:0]  s_addr;
  wire [31:0] s_din, s_dout;

  mem_ctrl dut (
    .clk(clk), .rstn(rstn),
    .psel(psel), .penable(penable), .pwrite(pwrite),
    .paddr(paddr), .pwdata(pwdata),
    .prdata(prdata), .pready(pready),
    .s_cs(s_cs), .s_we(s_we), .s_addr(s_addr),
    .s_din(s_din), .s_dout(s_dout)
  );

  sram_behav sram (
    .clk(clk), .cs(s_cs), .we(s_we),
    .addr(s_addr), .din(s_din), .dout(s_dout)
  );

  task apb_write(input [7:0] addr, input [31:0] data);
  begin
    @(negedge clk);
    psel=1; penable=1; pwrite=1; paddr=addr; pwdata=data;
    @(negedge clk);
    while (!pready) @(negedge clk);
    psel=0; penable=0; pwrite=0;
  end
  endtask

  task apb_read(input [7:0] addr, output [31:0] data);
  begin
    @(negedge clk);
    psel=1; penable=1; pwrite=0; paddr=addr;
    @(negedge clk);
    while (!pready) @(negedge clk);
    data = prdata;
    psel=0; penable=0;
  end
  endtask

  integer i;
  reg [31:0] rd;
  initial begin
    $dumpfile("out/dump.vcd");
    $dumpvars(0, tb_top);
    #20 rstn=1;
    for (i=0;i<4;i=i+1) apb_write(i[7:0], 32'hA5A50000 + i);
    for (i=0;i<4;i=i+1) begin
      apb_read(i[7:0], rd);
      if (rd !== (32'hA5A50000 + i)) $display("MISMATCH %0d exp=%h got=%h", i, (32'hA5A50000 + i), rd);
      else $display("OK %0d = %h", i, rd);
    end
    #50 $finish;
  end
endmodule

sim/dump.vcd
$date
	Wed Jan 14 10:52:41 2026
$end
$version
	Icarus Verilog
$end
$timescale
	1ps
$end
$scope module tb_top $end
$var wire 1 ! s_we $end
$var wire 32 " s_dout [31:0] $end
$var wire 32 # s_din [31:0] $end
$var wire 1 $ s_cs $end
$var wire 8 % s_addr [7:0] $end
$var wire 1 & pready $end
$var wire 32 ' prdata [31:0] $end
$var reg 1 ( clk $end
$var reg 8 ) paddr [7:0] $end
$var reg 1 * penable $end
$var reg 1 + psel $end
$var reg 32 , pwdata [31:0] $end
$var reg 1 - pwrite $end
$var reg 32 . rd [31:0] $end
$var reg 1 / rstn $end
$var integer 32 0 i [31:0] $end
$scope module dut $end
$var wire 1 ( clk $end
$var wire 8 1 paddr [7:0] $end
$var wire 1 * penable $end
$var wire 1 + psel $end
$var wire 32 2 pwdata [31:0] $end
$var wire 1 - pwrite $end
$var wire 1 / rstn $end
$var wire 32 3 s_dout [31:0] $end
$var parameter 32 4 ADDR_W $end
$var parameter 32 5 DATA_W $end
$var reg 1 6 pending $end
$var reg 32 7 prdata [31:0] $end
$var reg 1 & pready $end
$var reg 8 8 s_addr [7:0] $end
$var reg 1 $ s_cs $end
$var reg 32 9 s_din [31:0] $end
$var reg 1 ! s_we $end
$upscope $end
$scope module sram $end
$var wire 8 : addr [7:0] $end
$var wire 1 ( clk $end
$var wire 1 $ cs $end
$var wire 32 ; din [31:0] $end
$var wire 32 < dout [31:0] $end
$var wire 1 ! we $end
$var parameter 32 = ADDR_W $end
$var parameter 32 > DATA_W $end
$upscope $end
$scope task apb_read $end
$var reg 8 ? addr [7:0] $end
$var reg 32 @ data [31:0] $end
$upscope $end
$scope task apb_write $end
$var reg 8 A addr [7:0] $end
$var reg 32 B data [31:0] $end
$upscope $end
$upscope $end
$enddefinitions $end
$comment Show the parameter values. $end
$dumpall
b100000 >
b1000 =
b100000 5
b1000 4
$end
#0
$dumpvars
bx B
bx A
bx @
bx ?
bx <
bx ;
bx :
bx 9
bx 8
bx 7
x6
bx 3
b0 2
b0 1
bx 0
0/
bx .
0-
b0 ,
0+
0*
b0 )
0(
bx '
x&
bx %
x$
bx #
bx "
x!
$end
#5000
06
b0 #
b0 9
b0 ;
b0 %
b0 8
b0 :
0!
0$
b0 '
b0 7
0&
1(
#10000
0(
#15000
1(
#20000
b10100101101001010000000000000000 ,
b10100101101001010000000000000000 2
1-
1*
1+
0(
b10100101101001010000000000000000 B
b0 A
b0 0
1/
#25000
16
b10100101101001010000000000000000 #
b10100101101001010000000000000000 9
b10100101101001010000000000000000 ;
1!
1$
1(
#30000
0(
#35000
1!
1$
16
bx '
bx 7
1&
b10100101101001010000000000000000 "
b10100101101001010000000000000000 3
b10100101101001010000000000000000 <
1(
#40000
b10100101101001010000000000000001 B
b1 A
b1 0
0-
0*
0+
0(
#45000
0!
0$
06
b10100101101001010000000000000000 '
b10100101101001010000000000000000 7
1(
#50000
b10100101101001010000000000000001 ,
b10100101101001010000000000000001 2
b1 )
b1 1
1-
1*
1+
0(
#55000
16
b10100101101001010000000000000001 #
b10100101101001010000000000000001 9
b10100101101001010000000000000001 ;
bx "
bx 3
bx <
b1 %
b1 8
b1 :
1!
1$
0&
1(
#60000
0(
#65000
1!
1$
16
bx '
bx 7
1&
b10100101101001010000000000000001 "
b10100101101001010000000000000001 3
b10100101101001010000000000000001 <
1(
#70000
b10100101101001010000000000000010 B
b10 A
b10 0
0-
0*
0+
0(
#75000
0!
0$
06
b10100101101001010000000000000001 '
b10100101101001010000000000000001 7
1(
#80000
b10100101101001010000000000000010 ,
b10100101101001010000000000000010 2
b10 )
b10 1
1-
1*
1+
0(
#85000
16
b10100101101001010000000000000010 #
b10100101101001010000000000000010 9
b10100101101001010000000000000010 ;
bx "
bx 3
bx <
b10 %
b10 8
b10 :
1!
1$
0&
1(
#90000
0(
#95000
1!
1$
16
bx '
bx 7
1&
b10100101101001010000000000000010 "
b10100101101001010000000000000010 3
b10100101101001010000000000000010 <
1(
#100000
b10100101101001010000000000000011 B
b11 A
b11 0
0-
0*
0+
0(
#105000
0!
0$
06
b10100101101001010000000000000010 '
b10100101101001010000000000000010 7
1(
#110000
b10100101101001010000000000000011 ,
b10100101101001010000000000000011 2
b11 )
b11 1
1-
1*
1+
0(
#115000
16
b10100101101001010000000000000011 #
b10100101101001010000000000000011 9
b10100101101001010000000000000011 ;
bx "
bx 3
bx <
b11 %
b11 8
b11 :
1!
1$
0&
1(
#120000
0(
#125000
1!
1$
16
bx '
bx 7
1&
b10100101101001010000000000000011 "
b10100101101001010000000000000011 3
b10100101101001010000000000000011 <
1(
#130000
b0 ?
b0 0
0-
0*
0+
0(
#135000
0!
0$
06
b10100101101001010000000000000011 '
b10100101101001010000000000000011 7
1(
#140000
b0 )
b0 1
1*
1+
0(
#145000
16
b10100101101001010000000000000000 "
b10100101101001010000000000000000 3
b10100101101001010000000000000000 <
b0 %
b0 8
b0 :
1$
0&
1(
#150000
0(
#155000
1$
16
b10100101101001010000000000000000 '
b10100101101001010000000000000000 7
1&
1(
#160000
b1 ?
b1 0
b10100101101001010000000000000000 .
0*
0+
b10100101101001010000000000000000 @
0(
#165000
0$
06
1(
#170000
b1 )
b1 1
1*
1+
0(
#175000
16
b10100101101001010000000000000001 "
b10100101101001010000000000000001 3
b10100101101001010000000000000001 <
b1 %
b1 8
b1 :
1$
0&
1(
#180000
0(
#185000
1$
16
b10100101101001010000000000000001 '
b10100101101001010000000000000001 7
1&
1(
#190000
b10 ?
b10 0
b10100101101001010000000000000001 .
0*
0+
b10100101101001010000000000000001 @
0(
#195000
0$
06
1(
#200000
b10 )
b10 1
1*
1+
0(
#205000
16
b10100101101001010000000000000010 "
b10100101101001010000000000000010 3
b10100101101001010000000000000010 <
b10 %
b10 8
b10 :
1$
0&
1(
#210000
0(
#215000
1$
16
b10100101101001010000000000000010 '
b10100101101001010000000000000010 7
1&
1(
#220000
b11 ?
b11 0
b10100101101001010000000000000010 .
0*
0+
b10100101101001010000000000000010 @
0(
#225000
0$
06
1(
#230000
b11 )
b11 1
1*
1+
0(
#235000
16
b10100101101001010000000000000011 "
b10100101101001010000000000000011 3
b10100101101001010000000000000011 <
b11 %
b11 8
b11 :
1$
0&
1(
#240000
0(
#245000
1$
16
b10100101101001010000000000000011 '
b10100101101001010000000000000011 7
1&
1(
#250000
b100 0
b10100101101001010000000000000011 .
0*
0+
b10100101101001010000000000000011 @
0(
#255000
0$
06
1(
#260000
0(
#265000
0&
1(
